pyikuai/__init__.py
pyikuai/constants.py
pyikuai/core.py
pyikuai/exceptions.py
pyikuai-0.4.0.dev0.dist-info/LICENSE.txt
pyikuai-0.4.0.dev0.dist-info/METADATA
pyikuai-0.4.0.dev0.dist-info/WHEEL
pyikuai-0.4.0.dev0.dist-info/top_level.txt
pyikuai-0.4.0.dev0.dist-info/zip-safe
pyikuai-0.4.0.dev0.dist-info/RECORD
