Metadata-Version: 2.1
Name: pyikuai
Version: 0.4.0.dev0
Summary: A Python client for interacting with IKuai routers
Home-page: https://github.com/dzhuang/PyIKuaiClient/
Author: Dong Zhuang
Author-email: dzhuang.scut@gmail.com
License: MIT
Keywords: iKuai Router client API
Classifier: Development Status :: 3 - Alpha
Classifier: Environment :: Web Environment
Classifier: Intended Audience :: Developers
Classifier: License :: OSI Approved :: MIT License
Classifier: Operating System :: OS Independent
Classifier: Programming Language :: Python :: 3
Classifier: Programming Language :: Python :: 3 :: Only
Classifier: Programming Language :: Python :: 3.6
Classifier: Programming Language :: Python :: 3.7
Classifier: Programming Language :: Python :: 3.8
Classifier: Programming Language :: Python :: 3.9
Classifier: Topic :: Internet :: WWW/HTTP
Classifier: Topic :: Software Development :: Libraries :: Python Modules
Requires-Python: >=3.6
License-File: LICENSE.txt
Requires-Dist: requests
